{
	"key0": {
		"tags": [
			"#foodporn",
			"#러브잇"
		],
		"src": "https://scontent-ssn1-1.cdninstagram.com/v/t51.2885-15/e35/s1080x1080/120199618_653962548830739_1508605192386505021_n.jpg?_nc_ht=scontent-ssn1-1.cdninstagram.com&_nc_cat=103&_nc_ohc=5mh_oeQ_dNkAX_05UL-&_nc_tp=15&oh=0d2987fe514c40f573e8b6dce995742f&oe=5FD28964"
	},
	"key1": {
		"tags": [],
		"src": "https://scontent-ssn1-1.cdninstagram.com/v/t51.2885-15/e35/p1080x1080/123869149_1529248120796209_2865050967815298975_n.jpg?_nc_ht=scontent-ssn1-1.cdninstagram.com&_nc_cat=101&_nc_ohc=CI1g2PEpc5cAX-2C8qg&tp=19&oh=556e93d54d08e709b2544c22266fca13&oe=5FD1CCAC"
	},
	"key2": {
		"tags": [],
		"src": "https://scontent-ssn1-1.cdninstagram.com/v/t51.2885-15/e35/s1080x1080/123135000_268966744535249_3312430341431330941_n.jpg?_nc_ht=scontent-ssn1-1.cdninstagram.com&_nc_cat=105&_nc_ohc=sJ8AuOuz4FoAX_FJFQw&_nc_tp=15&oh=c5cefec2076bef246ebd291303262cea&oe=5FD2DC26"
	},
	"key3": {
		"tags": [
			"#까치둥지",
			"#먹스타그램",
			"#알탕맛집",
			"#맛있다그램",
			"#알탕",
			"#데일리",
			"#먹방",
			"#월요일",
			"#저녁",
			"#맞팔",
			"#koreanfood",
			"#팔로우",
			"#냠냠"
		],
		"src": "https://scontent-ssn1-1.cdninstagram.com/v/t51.2885-15/e15/121147604_3418960568195353_6452516627113375618_n.jpg?_nc_ht=scontent-ssn1-1.cdninstagram.com&_nc_cat=101&_nc_ohc=i_Wzas8HCIkAX_9YG9_&tp=18&oh=7dad4f68877b7790dc1c51881111ee7e&oe=5FD49063"
	},
	"key4": {
		"tags": [
			"#알탕",
			"#알곤이탕",
			"#먹스타그램",
			"#먹스타맞팔",
			"#먹팔",
			"#맞팔",
			"#f4f"
		],
		"src": "https://scontent-ssn1-1.cdninstagram.com/v/t51.2885-15/e35/120999607_338518037365598_687891885493093874_n.jpg?_nc_ht=scontent-ssn1-1.cdninstagram.com&_nc_cat=102&_nc_ohc=D7J358rLgwAAX-IeF2s&tp=18&oh=58d834e3e599a53a19314081b3e1028d&oe=5FD2AB1E"
	},
	"key5": {
		"tags": [
			"#협찬",
			"#아침식사",
			"#한식",
			"#동태알탕",
			"#알탕",
			"#백년밥상",
			"#집밥",
			"#홈쿡",
			"#엄마밥",
			"#가정식",
			"#동태탕",
			"#koreanfood",
			"#해장탕",
			"#인스타푸드",
			"#온더테이블"
		],
		"src": "https://scontent-ssn1-1.cdninstagram.com/v/t51.2885-15/e35/s1080x1080/122100180_345910820048033_2772916081166764698_n.jpg?_nc_ht=scontent-ssn1-1.cdninstagram.com&_nc_cat=105&_nc_ohc=K_u7HCV9DOAAX-Ys4aR&_nc_tp=15&oh=4da03b433086ab198a7515ca24830752&oe=5FD3C3A6"
	},
	"key6": {
		"tags": [
			"#알탕"
		],
		"src": "https://scontent-ssn1-1.cdninstagram.com/v/t51.2885-15/e35/s1080x1080/121668679_187152959520792_1074829139230543389_n.jpg?_nc_ht=scontent-ssn1-1.cdninstagram.com&_nc_cat=100&_nc_ohc=2SWI2grRGbIAX9F56Kk&_nc_tp=15&oh=0a1b39afae6848b52fb292d6158bc221&oe=5FD1FEA3"
	},
	"key7": {
		"tags": [
			"#다겐닭스",
			"#귤현점",
			"#다겐닭스귤현점",
			"#신메뉴",
			"#귤현맛집",
			"#맛집추천",
			"#치즈감자",
			"#명품알탕",
			"#새우완탕",
			"#알탕",
			"#얼큰알탕",
			"#차돌숙주볶음",
			"#새우튀김",
			"#차돌짬뽕탕"
		],
		"src": "https://scontent-ssn1-1.cdninstagram.com/v/t51.2885-15/e35/s1080x1080/121235198_3318757488172757_8653602916724785307_n.jpg?_nc_ht=scontent-ssn1-1.cdninstagram.com&_nc_cat=105&_nc_ohc=HLoE2e0SO-gAX-uH6_A&_nc_tp=15&oh=135c20cf02ce8fee633aebd83e5823e7&oe=5FD598BD"
	},
	"key8": {
		"tags": [],
		"src": "https://scontent-ssn1-1.cdninstagram.com/v/t51.2885-15/e35/s1080x1080/120843267_408554953467694_7449234179303396525_n.jpg?_nc_ht=scontent-ssn1-1.cdninstagram.com&_nc_cat=110&_nc_ohc=09VUFG6jMc4AX87grMj&_nc_tp=15&oh=59104bde31c69eba7ad73badc9f10670&oe=5FD5334E"
	},
	"key9": {
		"tags": [
			"#6",
			"#끓일래볶을래",
			"#동탄2신도시",
			"#카림3차",
			"#밀키트",
			"#가정간편식",
			"#집밥",
			"#동탄맛집",
			"#배달맛집",
			"#포장",
			"#동태탕",
			"#알탕",
			"#닭볶음탕",
			"#부대찌개",
			"#낙지볶음",
			"#오징어볶음",
			"#갈치조림",
			"#고등어조림",
			"#제육볶음",
			"#떡볶이",
			"#떡만두국",
			"#국물닭발",
			"#동탄호수공원",
			"#반도10차",
			"#반텐",
			"#반텐맛집",
			"#팔로우환영",
			"#캠핑요리",
			"#차박"
		],
		"src": "https://scontent-ssn1-1.cdninstagram.com/v/t51.2885-15/e35/s1080x1080/124064749_123234106035608_3016912194286890273_n.jpg?_nc_ht=scontent-ssn1-1.cdninstagram.com&_nc_cat=108&_nc_ohc=vG7n6Yf8jfsAX8Ai8cH&_nc_tp=15&oh=bd7db1d047dac2cdf123d3cda46aea40&oe=5FD1D86B"
	},
	"key10": {
		"tags": [
			"#맛스타그램",
			"#먹스타그램",
			"#먹스타맞팔",
			"#먹스타",
			"#맛집",
			"#메뉴추천",
			"#오늘뭐먹지",
			"#알탕",
			"#유부초밥",
			"#집밥"
		],
		"src": "https://scontent-ssn1-1.cdninstagram.com/v/t51.2885-15/e35/s1080x1080/123995393_718110822397247_3725223031518598087_n.jpg?_nc_ht=scontent-ssn1-1.cdninstagram.com&_nc_cat=111&_nc_ohc=V1Ff46PnxiAAX9TKLiA&_nc_tp=15&oh=b5172e9bc1ffab260ade205c72de3850&oe=5FD3DB54"
	},
	"key11": {
		"tags": [
			"#알탕",
			"#돌참치",
			"#구디",
			"#기분좋은점심"
		],
		"src": "https://scontent-ssn1-1.cdninstagram.com/v/t51.2885-15/e35/s1080x1080/124065184_400801487959491_1058735549768973989_n.jpg?_nc_ht=scontent-ssn1-1.cdninstagram.com&_nc_cat=103&_nc_ohc=foJZLPMO5OMAX9aL7tF&_nc_tp=15&oh=452e9c23c43f73d233c11011dd799eee&oe=5FD2AD19"
	}
}